env_channel/__init__.py
env_channel/client/__init__.py
env_channel/client/decorators.py
env_channel/client/publisher.py
env_channel/client/subscriber.py
env_channel/common/__init__.py
env_channel/common/exceptions.py
env_channel/common/filter.py
env_channel/common/message.py
env_channel/protocol/__init__.py
env_channel/protocol/websocket.py
env_channel/server/__init__.py
env_channel/server/channel_server.py
env_channel/server/connection_manager.py
env_channel/server/main.py
env_channel-0.1.0.dist-info/METADATA
env_channel-0.1.0.dist-info/WHEEL
env_channel-0.1.0.dist-info/RECORD
