Metadata-Version: 2.4
Name: env-channel
Version: 0.1.0
Summary: Bidirectional WebSocket channel SDK for MCP servers and Agent clients
License: MIT
Keywords: websocket,channel,mcp,sdk,async,messaging
Author: Your Name
Author-email: your.email@example.com
Requires-Python: >=3.10
Classifier: Development Status :: 3 - Alpha
Classifier: Intended Audience :: Developers
Classifier: License :: OSI Approved :: MIT License
Classifier: Programming Language :: Python :: 3
Classifier: Programming Language :: Python :: 3.10
Classifier: Programming Language :: Python :: 3.11
Classifier: Programming Language :: Python :: 3.12
Provides-Extra: dev
Provides-Extra: server
Requires-Dist: black (>=23.10.0) ; extra == "dev"
Requires-Dist: fastapi (>=0.104.0,<0.105.0) ; extra == "server"
Requires-Dist: mypy (>=1.6.0) ; extra == "dev"
Requires-Dist: pydantic (>=2.0,<3.0)
Requires-Dist: pytest (>=7.4.0) ; extra == "dev"
Requires-Dist: pytest-asyncio (>=0.21.0) ; extra == "dev"
Requires-Dist: python-socks (>=2.7.1)
Requires-Dist: ruff (>=0.1.0) ; extra == "dev"
Requires-Dist: typing-extensions (>=4.8,<5.0)
Requires-Dist: uvicorn (>=0.24.0,<0.25.0) ; extra == "server"
Requires-Dist: websockets (>=15.0.1)
Project-URL: Homepage, https://github.com/your-org/env-channel
Project-URL: Repository, https://github.com/your-org/env-channel
